[
    {
        "name": "id",
        "dbType": "increments",
        "htmlType": null,
        "validations": null,
        "searchable": false,
        "fillable": false,
        "primary": true,
        "inForm": false,
        "inIndex": false,
        "inView": false
    },
    {
        "name": "producto_id",
        "dbType": "integer:unsigned:foreign,productos,id",
        "htmlType": "select",
        "validations": "required",
        "searchable": true,
        "fillable": true,
        "primary": false,
        "inForm": true,
        "inIndex": true,
        "inView": true
    },
    {
        "name": "pedido_id",
        "dbType": "integer:unsigned:foreign,pedidos,id",
        "htmlType": "select",
        "validations": "required",
        "searchable": true,
        "fillable": true,
        "primary": false,
        "inForm": true,
        "inIndex": true,
        "inView": true
    },
    {
        "name": "cdet_cantidad",
        "dbType": "string",
        "htmlType": "input",
        "validations": "required",
        "searchable": true,
        "fillable": true,
        "primary": false,
        "inForm": true,
        "inIndex": true,
        "inView": true
    },
    {
        "name": "created_at",
        "dbType": "timestamp",
        "htmlType": null,
        "validations": null,
        "searchable": false,
        "fillable": false,
        "primary": false,
        "inForm": false,
        "inIndex": false,
        "inView": true
    },
    {
        "name": "updated_at",
        "dbType": "timestamp",
        "htmlType": null,
        "validations": null,
        "searchable": false,
        "fillable": false,
        "primary": false,
        "inForm": false,
        "inIndex": false,
        "inView": true
    }
]